comment_spell_check/__init__.py
comment_spell_check/additional_dictionary.txt
comment_spell_check/comment_spell_check.py
comment_spell_check/lib/__init__.py
comment_spell_check/lib/create_checker.py
comment_spell_check/utils/__init__.py
comment_spell_check/utils/bibtex_loader.py
comment_spell_check/utils/create_checker.py
comment_spell_check/utils/parseargs.py
comment_spell_check/utils/url_remove.py
comment_spell_check-0.4.4.dist-info/licenses/LICENSE
comment_spell_check-0.4.4.dist-info/METADATA
comment_spell_check-0.4.4.dist-info/WHEEL
comment_spell_check-0.4.4.dist-info/entry_points.txt
comment_spell_check-0.4.4.dist-info/top_level.txt
comment_spell_check-0.4.4.dist-info/RECORD
