Metadata-Version: 2.4
Name: comment_spell_check
Version: 0.4.4
Summary: A script to automatically spell checks comments of a codebase.
Author-email: David Chen <dchen@mail.nih.gov>
License: 
Project-URL: Homepage, https://github.com/SimpleITK/CommentSpellCheck
Project-URL: Bug Tracker, https://github.com/SimpleITK/CommentSpellCheck
Classifier: Programming Language :: Python :: 3
Classifier: License :: OSI Approved :: Apache Software License
Classifier: Operating System :: OS Independent
Requires-Python: >=3.8
License-File: LICENSE
Requires-Dist: comment_parser
Requires-Dist: pyspellchecker
Requires-Dist: bibtexparser
Requires-Dist: requests
Dynamic: license-file
